Classfile /C:/Users/INSUNG/Documents/dev/JVM-Compiler-ByteCode/javap/src/main/sourcecode/mytest/anonymous/inheritance/Hive$1.class
  Last modified 2023. 5. 3.; size 1410 bytes
  SHA-256 checksum be081f66c5fa98f5147a310d6cd1e1a409fd6ef3e5af7abf2c025d8feb058c0e
  Compiled from "Hive.java"
class main.sourcecode.anonymous.inheritance.Hive$1 extends main.sourcecode.anonymous.inheritance.Insect
  minor version: 0
  major version: 61
  flags: (0x0020) ACC_SUPER
  this_class: #2                          // main/sourcecode/mytest/anonymous/inheritance/Hive$1
  super_class: #8                         // main/sourcecode/mytest/anonymous/inheritance/Insect
  interfaces: 0, fields: 2, methods: 3, attributes: 5
Constant pool:
   #1 = Fieldref           #2.#3          // main/sourcecode/mytest/anonymous/inheritance/Hive$1.this$0:Lmain/sourcecode/mytest/anonymous/inheritance/Hive;
   #2 = Class              #4             // main/sourcecode/mytest/anonymous/inheritance/Hive$1
   #3 = NameAndType        #5:#6          // this$0:Lmain/sourcecode/mytest/anonymous/inheritance/Hive;
   #4 = Utf8               main/sourcecode/mytest/anonymous/inheritance/Hive$1
   #5 = Utf8               this$0
   #6 = Utf8               Lmain/sourcecode/mytest/anonymous/inheritance/Hive;
   #7 = Methodref          #8.#9          // main/sourcecode/mytest/anonymous/inheritance/Insect."<init>":()V
   #8 = Class              #10            // main/sourcecode/mytest/anonymous/inheritance/Insect
   #9 = NameAndType        #11:#12        // "<init>":()V
  #10 = Utf8               main/sourcecode/mytest/anonymous/inheritance/Insect
  #11 = Utf8               <init>
  #12 = Utf8               ()V
  #13 = String             #14            // 거미
  #14 = Utf8               거미
  #15 = Fieldref           #2.#16         // main/sourcecode/mytest/anonymous/inheritance/Hive$1.name:Ljava/lang/String;
  #16 = NameAndType        #17:#18        // name:Ljava/lang/String;
  #17 = Utf8               name
  #18 = Utf8               Ljava/lang/String;
  #19 = String             #20            // 무당
  #20 = Utf8               무당
  #21 = Fieldref           #2.#22         // main/sourcecode/mytest/anonymous/inheritance/Hive$1.spiderName:Ljava/lang/String;
  #22 = NameAndType        #23:#18        // spiderName:Ljava/lang/String;
  #23 = Utf8               spiderName
  #24 = Fieldref           #25.#26        // java/lang/System.out:Ljava/io/PrintStream;
  #25 = Class              #27            // java/lang/System
  #26 = NameAndType        #28:#29        // out:Ljava/io/PrintStream;
  #27 = Utf8               java/lang/System
  #28 = Utf8               out
  #29 = Utf8               Ljava/io/PrintStream;
  #30 = String             #31            // 거미줄을 친다
  #31 = Utf8               거미줄을 친다
  #32 = Methodref          #33.#34        // java/io/PrintStream.println:(Ljava/lang/String;)V
  #33 = Class              #35            // java/io/PrintStream
  #34 = NameAndType        #36:#37        // println:(Ljava/lang/String;)V
  #35 = Utf8               java/io/PrintStream
  #36 = Utf8               println
  #37 = Utf8               (Ljava/lang/String;)V
  #38 = InvokeDynamic      #0:#39         // #0:makeConcatWithConstants:(Ljava/lang/String;Ljava/lang/String;)Ljava/lang/String;
  #39 = NameAndType        #40:#41        // makeConcatWithConstants:(Ljava/lang/String;Ljava/lang/String;)Ljava/lang/String;
  #40 = Utf8               makeConcatWithConstants
  #41 = Utf8               (Ljava/lang/String;Ljava/lang/String;)Ljava/lang/String;
  #42 = Utf8               (Lmain/sourcecode/mytest/anonymous/inheritance/Hive;)V
  #43 = Utf8               Code
  #44 = Utf8               LineNumberTable
  #45 = Utf8               cobWeb
  #46 = Utf8               attack
  #47 = Utf8               SourceFile
  #48 = Utf8               Hive.java
  #49 = Utf8               EnclosingMethod
  #50 = Class              #51            // main/sourcecode/mytest/anonymous/inheritance/Hive
  #51 = Utf8               main/sourcecode/mytest/anonymous/inheritance/Hive
  #52 = Utf8               NestHost
  #53 = Utf8               BootstrapMethods
  #54 = MethodHandle       6:#55          // REF_invokeStatic java/lang/invoke/StringConcatFactory.makeConcatWithConstants:(Ljava/lang/invoke/MethodHandles$Lookup;Ljava/lang/String;Ljava/lang/invoke/MethodType;Ljava/lang/String;[Ljava/
lang/Object;)Ljava/lang/invoke/CallSite;
  #55 = Methodref          #56.#57        // java/lang/invoke/StringConcatFactory.makeConcatWithConstants:(Ljava/lang/invoke/MethodHandles$Lookup;Ljava/lang/String;Ljava/lang/invoke/MethodType;Ljava/lang/String;[Ljava/lang/Object;)Ljav
a/lang/invoke/CallSite;
  #56 = Class              #58            // java/lang/invoke/StringConcatFactory
  #57 = NameAndType        #40:#59        // makeConcatWithConstants:(Ljava/lang/invoke/MethodHandles$Lookup;Ljava/lang/String;Ljava/lang/invoke/MethodType;Ljava/lang/String;[Ljava/lang/Object;)Ljava/lang/invoke/CallSite;
  #58 = Utf8               java/lang/invoke/StringConcatFactory
  #59 = Utf8               (Ljava/lang/invoke/MethodHandles$Lookup;Ljava/lang/String;Ljava/lang/invoke/MethodType;Ljava/lang/String;[Ljava/lang/Object;)Ljava/lang/invoke/CallSite;
  #60 = String             #61            // \u0001-\u0001 : 독을 발사한다
  #61 = Utf8               \u0001-\u0001 : 독을 발사한다
  #62 = Utf8               InnerClasses
  #63 = Class              #64            // java/lang/invoke/MethodHandles$Lookup
  #64 = Utf8               java/lang/invoke/MethodHandles$Lookup
  #65 = Class              #66            // java/lang/invoke/MethodHandles
  #66 = Utf8               java/lang/invoke/MethodHandles
  #67 = Utf8               Lookup
{
  java.lang.String spiderName;
    descriptor: Ljava/lang/String;
    flags: (0x0000)

  final main.sourcecode.anonymous.inheritance.Hive this$0;
    descriptor: Lmain/sourcecode/mytest/anonymous/inheritance/Hive;
    flags: (0x1010) ACC_FINAL, ACC_SYNTHETIC

  main.sourcecode.anonymous.inheritance.Hive$1(main.sourcecode.anonymous.inheritance.Hive);
    descriptor: (Lmain/sourcecode/mytest/anonymous/inheritance/Hive;)V
    flags: (0x0000)
    Code:
      stack=2, locals=2, args_size=2
         0: aload_0
         1: aload_1
         2: putfield      #1                  // Field this$0:Lmain/sourcecode/mytest/anonymous/inheritance/Hive;
         5: aload_0
         6: invokespecial #7                  // Method main/sourcecode/mytest/anonymous/inheritance/Insect."<init>":()V
         9: aload_0
        10: ldc           #13                 // String 거미
        12: putfield      #15                 // Field name:Ljava/lang/String;
        15: aload_0
        16: ldc           #19                 // String 무당
        18: putfield      #21                 // Field spiderName:Ljava/lang/String;
        21: return
      LineNumberTable:
        line 6: 0
        line 9: 9
        line 10: 15
        line 11: 21

  void cobWeb();
    descriptor: ()V
    flags: (0x0000)
    Code:
      stack=2, locals=1, args_size=1
         0: getstatic     #24                 // Field java/lang/System.out:Ljava/io/PrintStream;
         3: ldc           #30                 // String 거미줄을 친다
         5: invokevirtual #32                 // Method java/io/PrintStream.println:(Ljava/lang/String;)V
         8: return
      LineNumberTable:
        line 15: 0
        line 16: 8

  public void attack();
    descriptor: ()V
    flags: (0x0001) ACC_PUBLIC
    Code:
      stack=3, locals=1, args_size=1
         0: getstatic     #24                 // Field java/lang/System.out:Ljava/io/PrintStream;
         3: aload_0
         4: getfield      #21                 // Field spiderName:Ljava/lang/String;
         7: aload_0
         8: getfield      #15                 // Field name:Ljava/lang/String;
        11: invokedynamic #38,  0             // InvokeDynamic #0:makeConcatWithConstants:(Ljava/lang/String;Ljava/lang/String;)Ljava/lang/String;
        16: invokevirtual #32                 // Method java/io/PrintStream.println:(Ljava/lang/String;)V
        19: return
      LineNumberTable:
        line 20: 0
        line 21: 19
}
SourceFile: "Hive.java"
EnclosingMethod: #50.#0                 // main.sourcecode.anonymous.inheritance.Hive
NestHost: class main/sourcecode/mytest/anonymous/inheritance/Hive
BootstrapMethods:
  0: #54 REF_invokeStatic java/lang/invoke/StringConcatFactory.makeConcatWithConstants:(Ljava/lang/invoke/MethodHandles$Lookup;Ljava/lang/String;Ljava/lang/invoke/MethodType;Ljava/lang/String;[Ljava/lang/Object;)Ljava/lang/invoke/CallS
ite;
    Method arguments:
      #60 \u0001-\u0001 : 독을 발사한다
InnerClasses:
  #2;                                     // class main/sourcecode/mytest/anonymous/inheritance/Hive$1
  public static final #67= #63 of #65;    // Lookup=class java/lang/invoke/MethodHandles$Lookup of class java/lang/invoke/MethodHandles
