Classfile /C:/Users/INSUNG/Documents/dev/JVM-Compiler-ByteCode/javap/src/main/sourcecode/mytest/inner/localclass/OuterClass$1LocalClass.class
  Last modified 2023. 4. 29.; size 1198 bytes
  SHA-256 checksum e468227369c5a9d606538459c688812b80cc389704b68fa4a9de56e305c90348
  Compiled from "OuterClass.java"
class main.sourcecode.innerAdvanced2.localclass.OuterClass$1LocalClass
  minor version: 0
  major version: 61
  flags: (0x0020) ACC_SUPER
  this_class: #2                          // main/sourcecode/mytest/inner/localclass/OuterClass$1LocalClass
  super_class: #8                         // java/lang/Object
  interfaces: 0, fields: 2, methods: 2, attributes: 5
Constant pool:
   #1 = Fieldref           #2.#3          // main/sourcecode/mytest/inner/localclass/OuterClass$1LocalClass.this$0:Lmain/sourcecode/mytest/inner/localclass/OuterClass;
   #2 = Class              #4             // main/sourcecode/mytest/inner/localclass/OuterClass$1LocalClass
   #3 = NameAndType        #5:#6          // this$0:Lmain/sourcecode/mytest/inner/localclass/OuterClass;
   #4 = Utf8               main/sourcecode/mytest/inner/localclass/OuterClass$1LocalClass
   #5 = Utf8               this$0
   #6 = Utf8               Lmain/sourcecode/mytest/inner/localclass/OuterClass;
   #7 = Methodref          #8.#9          // java/lang/Object."<init>":()V
   #8 = Class              #10            // java/lang/Object
   #9 = NameAndType        #11:#12        // "<init>":()V
  #10 = Utf8               java/lang/Object
  #11 = Utf8               <init>
  #12 = Utf8               ()V
  #13 = Fieldref           #14.#15        // java/lang/System.out:Ljava/io/PrintStream;
  #14 = Class              #16            // java/lang/System
  #15 = NameAndType        #17:#18        // out:Ljava/io/PrintStream;
  #16 = Utf8               java/lang/System
  #17 = Utf8               out
  #18 = Utf8               Ljava/io/PrintStream;
  #19 = Fieldref           #2.#20         // main/sourcecode/mytest/inner/localclass/OuterClass$1LocalClass.d:I
  #20 = NameAndType        #21:#22        // d:I
  #21 = Utf8               d
  #22 = Utf8               I
  #23 = InvokeDynamic      #0:#24         // #0:makeConcatWithConstants:(I)Ljava/lang/String;
  #24 = NameAndType        #25:#26        // makeConcatWithConstants:(I)Ljava/lang/String;
  #25 = Utf8               makeConcatWithConstants
  #26 = Utf8               (I)Ljava/lang/String;
  #27 = Methodref          #28.#29        // java/io/PrintStream.println:(Ljava/lang/String;)V
  #28 = Class              #30            // java/io/PrintStream
  #29 = NameAndType        #31:#32        // println:(Ljava/lang/String;)V
  #30 = Utf8               java/io/PrintStream
  #31 = Utf8               println
  #32 = Utf8               (Ljava/lang/String;)V
  #33 = Utf8               (Lmain/sourcecode/mytest/inner/localclass/OuterClass;)V
  #34 = Utf8               Code
  #35 = Utf8               LineNumberTable
  #36 = Utf8               method2
  #37 = Utf8               SourceFile
  #38 = Utf8               OuterClass.java
  #39 = Utf8               EnclosingMethod
  #40 = Class              #41            // main/sourcecode/mytest/inner/localclass/OuterClass
  #41 = Utf8               main/sourcecode/mytest/inner/localclass/OuterClass
  #42 = NameAndType        #43:#12        // method1:()V
  #43 = Utf8               method1
  #44 = Utf8               NestHost
  #45 = Utf8               BootstrapMethods
  #46 = MethodHandle       6:#47          // REF_invokeStatic java/lang/invoke/StringConcatFactory.makeConcatWithConstants:(Ljava/lang/invoke/MethodHandles$Lookup;Ljava/lang/String;Ljava/lang/invoke/MethodType;Ljava/lang/String;[Ljava/
lang/Object;)Ljava/lang/invoke/CallSite;
  #47 = Methodref          #48.#49        // java/lang/invoke/StringConcatFactory.makeConcatWithConstants:(Ljava/lang/invoke/MethodHandles$Lookup;Ljava/lang/String;Ljava/lang/invoke/MethodType;Ljava/lang/String;[Ljava/lang/Object;)Ljav
a/lang/invoke/CallSite;
  #48 = Class              #50            // java/lang/invoke/StringConcatFactory
  #49 = NameAndType        #25:#51        // makeConcatWithConstants:(Ljava/lang/invoke/MethodHandles$Lookup;Ljava/lang/String;Ljava/lang/invoke/MethodType;Ljava/lang/String;[Ljava/lang/Object;)Ljava/lang/invoke/CallSite;
  #50 = Utf8               java/lang/invoke/StringConcatFactory
  #51 = Utf8               (Ljava/lang/invoke/MethodHandles$Lookup;Ljava/lang/String;Ljava/lang/invoke/MethodType;Ljava/lang/String;[Ljava/lang/Object;)Ljava/lang/invoke/CallSite;
  #52 = String             #53            // LocalClass : \u0001
  #53 = Utf8               LocalClass : \u0001
  #54 = Utf8               InnerClasses
  #55 = Utf8               LocalClass
  #56 = Class              #57            // java/lang/invoke/MethodHandles$Lookup
  #57 = Utf8               java/lang/invoke/MethodHandles$Lookup
  #58 = Class              #59            // java/lang/invoke/MethodHandles
  #59 = Utf8               java/lang/invoke/MethodHandles
  #60 = Utf8               Lookup
{
  int d;
    descriptor: I
    flags: (0x0000)

  final main.sourcecode.innerAdvanced2.localclass.OuterClass this$0;
    descriptor: Lmain/sourcecode/mytest/inner/localclass/OuterClass;
    flags: (0x1010) ACC_FINAL, ACC_SYNTHETIC

  main.sourcecode.innerAdvanced2.localclass.OuterClass$1LocalClass(main.sourcecode.innerAdvanced2.localclass.OuterClass);
    descriptor: (Lmain/sourcecode/mytest/inner/localclass/OuterClass;)V
    flags: (0x0000)
    Code:
      stack=2, locals=2, args_size=2
         0: aload_0
         1: aload_1
         2: putfield      #1                  // Field this$0:Lmain/sourcecode/mytest/inner/localclass/OuterClass;
         5: aload_0
         6: invokespecial #7                  // Method java/lang/Object."<init>":()V
         9: return
      LineNumberTable:
        line 7: 0

  void method2();
    descriptor: ()V
    flags: (0x0000)
    Code:
      stack=2, locals=1, args_size=1
         0: getstatic     #13                 // Field java/lang/System.out:Ljava/io/PrintStream;
         3: aload_0
         4: getfield      #19                 // Field d:I
         7: invokedynamic #23,  0             // InvokeDynamic #0:makeConcatWithConstants:(I)Ljava/lang/String;
        12: invokevirtual #27                 // Method java/io/PrintStream.println:(Ljava/lang/String;)V
        15: return
      LineNumberTable:
        line 11: 0
        line 12: 15
}
SourceFile: "OuterClass.java"
EnclosingMethod: #40.#42                // main.sourcecode.innerAdvanced2.localclass.OuterClass.method1
NestHost: class main/sourcecode/mytest/inner/localclass/OuterClass
BootstrapMethods:
  0: #46 REF_invokeStatic java/lang/invoke/StringConcatFactory.makeConcatWithConstants:(Ljava/lang/invoke/MethodHandles$Lookup;Ljava/lang/String;Ljava/lang/invoke/MethodType;Ljava/lang/String;[Ljava/lang/Object;)Ljava/lang/invoke/CallS
ite;
    Method arguments:
      #52 LocalClass : \u0001
InnerClasses:
  #55= #2;                                // LocalClass=class main/sourcecode/mytest/inner/localclass/OuterClass$1LocalClass
  public static final #60= #56 of #58;    // Lookup=class java/lang/invoke/MethodHandles$Lookup of class java/lang/invoke/MethodHandles
