Classfile /C:/Users/INSUNG/Documents/dev/JVM-Compiler-ByteCode/javap/src/main/sourcecode/mytest/anonymous/inheritance/Hive.class
  Last modified 2023. 5. 3.; size 666 bytes
  SHA-256 checksum 314db8a971aeb67c1a3d37663df71b86af5524a6825e9a3b739ee454b678fde6
  Compiled from "Hive.java"
public class main.sourcecode.anonymous.inheritance.Hive
  minor version: 0
  major version: 61
  flags: (0x0021) ACC_PUBLIC, ACC_SUPER
  this_class: #13                         // main/sourcecode/mytest/anonymous/inheritance/Hive
  super_class: #2                         // java/lang/Object
  interfaces: 0, fields: 2, methods: 2, attributes: 3
Constant pool:
   #1 = Methodref          #2.#3          // java/lang/Object."<init>":()V
   #2 = Class              #4             // java/lang/Object
   #3 = NameAndType        #5:#6          // "<init>":()V
   #4 = Utf8               java/lang/Object
   #5 = Utf8               <init>
   #6 = Utf8               ()V
   #7 = Class              #8             // main/sourcecode/mytest/anonymous/inheritance/Hive$1
   #8 = Utf8               main/sourcecode/mytest/anonymous/inheritance/Hive$1
   #9 = Methodref          #7.#10         // main/sourcecode/mytest/anonymous/inheritance/Hive$1."<init>":(Lmain/sourcecode/mytest/anonymous/inheritance/Hive;)V
  #10 = NameAndType        #5:#11         // "<init>":(Lmain/sourcecode/mytest/anonymous/inheritance/Hive;)V
  #11 = Utf8               (Lmain/sourcecode/mytest/anonymous/inheritance/Hive;)V
  #12 = Fieldref           #13.#14        // main/sourcecode/mytest/anonymous/inheritance/Hive.spider1:Lmain/sourcecode/mytest/anonymous/inheritance/Insect;
  #13 = Class              #15            // main/sourcecode/mytest/anonymous/inheritance/Hive
  #14 = NameAndType        #16:#17        // spider1:Lmain/sourcecode/mytest/anonymous/inheritance/Insect;
  #15 = Utf8               main/sourcecode/mytest/anonymous/inheritance/Hive
  #16 = Utf8               spider1
  #17 = Utf8               Lmain/sourcecode/mytest/anonymous/inheritance/Insect;
  #18 = Class              #19            // main/sourcecode/mytest/anonymous/inheritance/Hive$2
  #19 = Utf8               main/sourcecode/mytest/anonymous/inheritance/Hive$2
  #20 = Methodref          #18.#3         // main/sourcecode/mytest/anonymous/inheritance/Hive$2."<init>":()V
  #21 = Fieldref           #13.#22        // main/sourcecode/mytest/anonymous/inheritance/Hive.spider2:Lmain/sourcecode/mytest/anonymous/inheritance/Insect;
  #22 = NameAndType        #23:#17        // spider2:Lmain/sourcecode/mytest/anonymous/inheritance/Insect;
  #23 = Utf8               spider2
  #24 = Utf8               Code
  #25 = Utf8               LineNumberTable
  #26 = Utf8               <clinit>
  #27 = Utf8               SourceFile
  #28 = Utf8               Hive.java
  #29 = Utf8               NestMembers
  #30 = Utf8               InnerClasses
{
  main.sourcecode.anonymous.inheritance.Insect spider1;
    descriptor: Lmain/sourcecode/mytest/anonymous/inheritance/Insect;
    flags: (0x0000)

  static main.sourcecode.anonymous.inheritance.Insect spider2;
    descriptor: Lmain/sourcecode/mytest/anonymous/inheritance/Insect;
    flags: (0x0008) ACC_STATIC

  public main.sourcecode.anonymous.inheritance.Hive();
    descriptor: ()V
    flags: (0x0001) ACC_PUBLIC
    Code:
      stack=4, locals=1, args_size=1
         0: aload_0
         1: invokespecial #1                  // Method java/lang/Object."<init>":()V
         4: aload_0
         5: new           #7                  // class main/sourcecode/mytest/anonymous/inheritance/Hive$1
         8: dup
         9: aload_0
        10: invokespecial #9                  // Method main/sourcecode/mytest/anonymous/inheritance/Hive$1."<init>":(Lmain/sourcecode/mytest/anonymous/inheritance/Hive;)V
        13: putfield      #12                 // Field spider1:Lmain/sourcecode/mytest/anonymous/inheritance/Insect;
        16: return
      LineNumberTable:
        line 3: 0
        line 6: 4

  static {};
    descriptor: ()V
    flags: (0x0008) ACC_STATIC
    Code:
      stack=2, locals=0, args_size=0
         0: new           #18                 // class main/sourcecode/mytest/anonymous/inheritance/Hive$2
         3: dup
         4: invokespecial #20                 // Method main/sourcecode/mytest/anonymous/inheritance/Hive$2."<init>":()V
         7: putstatic     #21                 // Field spider2:Lmain/sourcecode/mytest/anonymous/inheritance/Insect;
        10: return
      LineNumberTable:
        line 24: 0
}
SourceFile: "Hive.java"
NestMembers:
  main/sourcecode/mytest/anonymous/inheritance/Hive$2
  main/sourcecode/mytest/anonymous/inheritance/Hive$1
InnerClasses:
  #7;                                     // class main/sourcecode/mytest/anonymous/inheritance/Hive$1
  #18;                                    // class main/sourcecode/mytest/anonymous/inheritance/Hive$2
