Classfile /C:/Users/INSUNG/Documents/dev/JVM-Compiler-ByteCode/javap/src/main/sourcecode/implementation/GalaxyMessanger.class
  Last modified 2023. 4. 19.; size 1480 bytes
  SHA-256 checksum 89a29cbc007f39e21cc56f28eaa025d1a00fe9044dc932a734d97ea83a012f1b
  Compiled from "GalaxyMessanger.java"
public class main.sourcecode.implementation.GalaxyMessanger implements main.sourcecode.implementation.Messanger,main.sourcecode.implementation.WorkFile
  minor version: 0
  major version: 61
  flags: (0x0021) ACC_PUBLIC, ACC_SUPER
  this_class: #28                         // main/sourcecode/implementation/GalaxyMessanger
  super_class: #2                         // java/lang/Object
  interfaces: 2, fields: 0, methods: 6, attributes: 3
Constant pool:
   #1 = Methodref          #2.#3          // java/lang/Object."<init>":()V
   #2 = Class              #4             // java/lang/Object
   #3 = NameAndType        #5:#6          // "<init>":()V
   #4 = Utf8               java/lang/Object
   #5 = Utf8               <init>
   #6 = Utf8               ()V
   #7 = String             #8             // Galaxy
   #8 = Utf8               Galaxy
   #9 = Fieldref           #10.#11        // java/lang/System.out:Ljava/io/PrintStream;
  #10 = Class              #12            // java/lang/System
  #11 = NameAndType        #13:#14        // out:Ljava/io/PrintStream;
  #12 = Utf8               java/lang/System
  #13 = Utf8               out
  #14 = Utf8               Ljava/io/PrintStream;
  #15 = InvokeDynamic      #0:#16         // #0:makeConcatWithConstants:(Ljava/lang/String;)Ljava/lang/String;
  #16 = NameAndType        #17:#18        // makeConcatWithConstants:(Ljava/lang/String;)Ljava/lang/String;
  #17 = Utf8               makeConcatWithConstants
  #18 = Utf8               (Ljava/lang/String;)Ljava/lang/String;
  #19 = Methodref          #20.#21        // java/io/PrintStream.println:(Ljava/lang/String;)V
  #20 = Class              #22            // java/io/PrintStream
  #21 = NameAndType        #23:#24        // println:(Ljava/lang/String;)V
  #22 = Utf8               java/io/PrintStream
  #23 = Utf8               println
  #24 = Utf8               (Ljava/lang/String;)V
  #25 = String             #26            // 키보드 아이콘 터치 후 키보드를 변경합니다.
  #26 = Utf8               키보드 아이콘 터치 후 키보드를 변경합니다.
  #27 = Methodref          #28.#29        // main/sourcecode/implementation/GalaxyMessanger.workingOn:()V
  #28 = Class              #30            // main/sourcecode/implementation/GalaxyMessanger
  #29 = NameAndType        #31:#6         // workingOn:()V
  #30 = Utf8               main/sourcecode/implementation/GalaxyMessanger
  #31 = Utf8               workingOn
  #32 = String             #33            // file을 다운로드 합니다
  #33 = Utf8               file을 다운로드 합니다
  #34 = String             #35            // file을 업로드 합니다
  #35 = Utf8               file을 업로드 합니다
  #36 = Class              #37            // main/sourcecode/implementation/Messanger
  #37 = Utf8               main/sourcecode/implementation/Messanger
  #38 = Class              #39            // main/sourcecode/implementation/WorkFile
  #39 = Utf8               main/sourcecode/implementation/WorkFile
  #40 = Utf8               Code
  #41 = Utf8               LineNumberTable
  #42 = Utf8               getMessage
  #43 = Utf8               ()Ljava/lang/String;
  #44 = Utf8               setMessage
  #45 = Utf8               changeKeyboard
  #46 = Utf8               fileUpload
  #47 = Utf8               fileDownload
  #48 = Utf8               SourceFile
  #49 = Utf8               GalaxyMessanger.java
  #50 = Utf8               BootstrapMethods
  #51 = MethodHandle       6:#52          // REF_invokeStatic java/lang/invoke/StringConcatFactory.makeConcatWithConstants:(Ljava/lang/invoke/MethodHandles$Lookup;Ljava/lang/String;Ljava/lang/invoke/MethodType;Ljava/lang/String;[Ljava/
lang/Object;)Ljava/lang/invoke/CallSite;
  #52 = Methodref          #53.#54        // java/lang/invoke/StringConcatFactory.makeConcatWithConstants:(Ljava/lang/invoke/MethodHandles$Lookup;Ljava/lang/String;Ljava/lang/invoke/MethodType;Ljava/lang/String;[Ljava/lang/Object;)Ljav
a/lang/invoke/CallSite;
  #53 = Class              #55            // java/lang/invoke/StringConcatFactory
  #54 = NameAndType        #17:#56        // makeConcatWithConstants:(Ljava/lang/invoke/MethodHandles$Lookup;Ljava/lang/String;Ljava/lang/invoke/MethodType;Ljava/lang/String;[Ljava/lang/Object;)Ljava/lang/invoke/CallSite;
  #55 = Utf8               java/lang/invoke/StringConcatFactory
  #56 = Utf8               (Ljava/lang/invoke/MethodHandles$Lookup;Ljava/lang/String;Ljava/lang/invoke/MethodType;Ljava/lang/String;[Ljava/lang/Object;)Ljava/lang/invoke/CallSite;
  #57 = String             #58            // Galaxy에서 메시지를 설정합니다 : \u0001
  #58 = Utf8               Galaxy에서 메시지를 설정합니다 : \u0001
  #59 = Utf8               InnerClasses
  #60 = Class              #61            // java/lang/invoke/MethodHandles$Lookup
  #61 = Utf8               java/lang/invoke/MethodHandles$Lookup
  #62 = Class              #63            // java/lang/invoke/MethodHandles
  #63 = Utf8               java/lang/invoke/MethodHandles
  #64 = Utf8               Lookup
{
  public main.sourcecode.implementation.GalaxyMessanger();
    descriptor: ()V
    flags: (0x0001) ACC_PUBLIC
    Code:
      stack=1, locals=1, args_size=1
         0: aload_0
         1: invokespecial #1                  // Method java/lang/Object."<init>":()V
         4: return
      LineNumberTable:
        line 3: 0

  public java.lang.String getMessage();
    descriptor: ()Ljava/lang/String;
    flags: (0x0001) ACC_PUBLIC
    Code:
      stack=1, locals=1, args_size=1
         0: ldc           #7                  // String Galaxy
         2: areturn
      LineNumberTable:
        line 7: 0

  public void setMessage(java.lang.String);
    descriptor: (Ljava/lang/String;)V
    flags: (0x0001) ACC_PUBLIC
    Code:
      stack=2, locals=2, args_size=2
         0: getstatic     #9                  // Field java/lang/System.out:Ljava/io/PrintStream;
         3: aload_1
         4: invokedynamic #15,  0             // InvokeDynamic #0:makeConcatWithConstants:(Ljava/lang/String;)Ljava/lang/String;
         9: invokevirtual #19                 // Method java/io/PrintStream.println:(Ljava/lang/String;)V
        12: return
      LineNumberTable:
        line 12: 0
        line 13: 12

  public void changeKeyboard();
    descriptor: ()V
    flags: (0x0001) ACC_PUBLIC
    Code:
      stack=2, locals=1, args_size=1
         0: getstatic     #9                  // Field java/lang/System.out:Ljava/io/PrintStream;
         3: ldc           #25                 // String 키보드 아이콘 터치 후 키보드를 변경합니다.
         5: invokevirtual #19                 // Method java/io/PrintStream.println:(Ljava/lang/String;)V
         8: return
      LineNumberTable:
        line 16: 0
        line 17: 8

  public void fileUpload();
    descriptor: ()V
    flags: (0x0001) ACC_PUBLIC
    Code:
      stack=2, locals=1, args_size=1
         0: aload_0
         1: invokevirtual #27                 // Method workingOn:()V
         4: getstatic     #9                  // Field java/lang/System.out:Ljava/io/PrintStream;
         7: ldc           #32                 // String file을 다운로드 합니다
         9: invokevirtual #19                 // Method java/io/PrintStream.println:(Ljava/lang/String;)V
        12: return
      LineNumberTable:
        line 22: 0
        line 23: 4
        line 24: 12

  public void fileDownload();
    descriptor: ()V
    flags: (0x0001) ACC_PUBLIC
    Code:
      stack=2, locals=1, args_size=1
         0: aload_0
         1: invokevirtual #27                 // Method workingOn:()V
         4: getstatic     #9                  // Field java/lang/System.out:Ljava/io/PrintStream;
         7: ldc           #34                 // String file을 업로드 합니다
         9: invokevirtual #19                 // Method java/io/PrintStream.println:(Ljava/lang/String;)V
        12: return
      LineNumberTable:
        line 28: 0
        line 29: 4
        line 30: 12
}
SourceFile: "GalaxyMessanger.java"
BootstrapMethods:
  0: #51 REF_invokeStatic java/lang/invoke/StringConcatFactory.makeConcatWithConstants:(Ljava/lang/invoke/MethodHandles$Lookup;Ljava/lang/String;Ljava/lang/invoke/MethodType;Ljava/lang/String;[Ljava/lang/Object;)Ljava/lang/invoke/CallS
ite;
    Method arguments:
      #57 Galaxy에서 메시지를 설정합니다 : \u0001
InnerClasses:
  public static final #64= #60 of #62;    // Lookup=class java/lang/invoke/MethodHandles$Lookup of class java/lang/invoke/MethodHandles
