Classfile /C:/Users/INSUNG/Documents/dev/JVM-Compiler-ByteCode/javap/src/main/sourcecode/implementation/WorkFile.class
  Last modified 2023. 4. 19.; size 1133 bytes
  SHA-256 checksum 15d8cfeed66c45a6823323cd0635612f50370172a988ecbf5bad2a0f3ec30cd4
  Compiled from "WorkFile.java"
public interface main.sourcecode.implementation.WorkFile
  minor version: 0
  major version: 61
  flags: (0x0601) ACC_PUBLIC, ACC_INTERFACE, ACC_ABSTRACT
  this_class: #2                          // main/sourcecode/implementation/WorkFile
  super_class: #27                        // java/lang/Object
  interfaces: 0, fields: 2, methods: 4, attributes: 3
Constant pool:
   #1 = InterfaceMethodref #2.#3          // main/sourcecode/implementation/WorkFile.log:()Ljava/lang/String;
   #2 = Class              #4             // main/sourcecode/implementation/WorkFile
   #3 = NameAndType        #5:#6          // log:()Ljava/lang/String;
   #4 = Utf8               main/sourcecode/implementation/WorkFile
   #5 = Utf8               log
   #6 = Utf8               ()Ljava/lang/String;
   #7 = Fieldref           #8.#9          // java/lang/System.out:Ljava/io/PrintStream;
   #8 = Class              #10            // java/lang/System
   #9 = NameAndType        #11:#12        // out:Ljava/io/PrintStream;
  #10 = Utf8               java/lang/System
  #11 = Utf8               out
  #12 = Utf8               Ljava/io/PrintStream;
  #13 = InvokeDynamic      #0:#14         // #0:makeConcatWithConstants:(Ljava/lang/String;)Ljava/lang/String;
  #14 = NameAndType        #15:#16        // makeConcatWithConstants:(Ljava/lang/String;)Ljava/lang/String;
  #15 = Utf8               makeConcatWithConstants
  #16 = Utf8               (Ljava/lang/String;)Ljava/lang/String;
  #17 = Methodref          #18.#19        // java/io/PrintStream.println:(Ljava/lang/String;)V
  #18 = Class              #20            // java/io/PrintStream
  #19 = NameAndType        #21:#22        // println:(Ljava/lang/String;)V
  #20 = Utf8               java/io/PrintStream
  #21 = Utf8               println
  #22 = Utf8               (Ljava/lang/String;)V
  #23 = String             #24            // WorkFile 로깅 시작
  #24 = Utf8               WorkFile 로깅 시작
  #25 = String             #26            // version : blue
  #26 = Utf8               version : blue
  #27 = Class              #28            // java/lang/Object
  #28 = Utf8               java/lang/Object
  #29 = Utf8               VERSION
  #30 = Utf8               D
  #31 = Utf8               ConstantValue
  #32 = Double             1.0d
  #34 = Utf8               VERSION_NAME
  #35 = Utf8               Ljava/lang/String;
  #36 = String             #37            // blue
  #37 = Utf8               blue
  #38 = Utf8               fileUpload
  #39 = Utf8               ()V
  #40 = Utf8               fileDownload
  #41 = Utf8               workingOn
  #42 = Utf8               Code
  #43 = Utf8               LineNumberTable
  #44 = Utf8               SourceFile
  #45 = Utf8               WorkFile.java
  #46 = Utf8               BootstrapMethods
  #47 = MethodHandle       6:#48          // REF_invokeStatic java/lang/invoke/StringConcatFactory.makeConcatWithConstants:(Ljava/lang/invoke/MethodHandles$Lookup;Ljava/lang/String;Ljava/lang/invoke/MethodType;Ljava/lang/String;[Ljava/
lang/Object;)Ljava/lang/invoke/CallSite;
  #48 = Methodref          #49.#50        // java/lang/invoke/StringConcatFactory.makeConcatWithConstants:(Ljava/lang/invoke/MethodHandles$Lookup;Ljava/lang/String;Ljava/lang/invoke/MethodType;Ljava/lang/String;[Ljava/lang/Object;)Ljav
a/lang/invoke/CallSite;
  #49 = Class              #51            // java/lang/invoke/StringConcatFactory
  #50 = NameAndType        #15:#52        // makeConcatWithConstants:(Ljava/lang/invoke/MethodHandles$Lookup;Ljava/lang/String;Ljava/lang/invoke/MethodType;Ljava/lang/String;[Ljava/lang/Object;)Ljava/lang/invoke/CallSite;
  #51 = Utf8               java/lang/invoke/StringConcatFactory
  #52 = Utf8               (Ljava/lang/invoke/MethodHandles$Lookup;Ljava/lang/String;Ljava/lang/invoke/MethodType;Ljava/lang/String;[Ljava/lang/Object;)Ljava/lang/invoke/CallSite;
  #53 = String             #54            // workingOn() with \u0001
  #54 = Utf8               workingOn() with \u0001
  #55 = Utf8               InnerClasses
  #56 = Class              #57            // java/lang/invoke/MethodHandles$Lookup
  #57 = Utf8               java/lang/invoke/MethodHandles$Lookup
  #58 = Class              #59            // java/lang/invoke/MethodHandles
  #59 = Utf8               java/lang/invoke/MethodHandles
  #60 = Utf8               Lookup
{
  public static final double VERSION;
    descriptor: D
    flags: (0x0019) ACC_PUBLIC, ACC_STATIC, ACC_FINAL
    ConstantValue: double 1.0d

  public static final java.lang.String VERSION_NAME;
    descriptor: Ljava/lang/String;
    flags: (0x0019) ACC_PUBLIC, ACC_STATIC, ACC_FINAL
    ConstantValue: String blue

  public abstract void fileUpload();
    descriptor: ()V
    flags: (0x0401) ACC_PUBLIC, ACC_ABSTRACT

  public abstract void fileDownload();
    descriptor: ()V
    flags: (0x0401) ACC_PUBLIC, ACC_ABSTRACT

  public default void workingOn();
    descriptor: ()V
    flags: (0x0001) ACC_PUBLIC
    Code:
      stack=2, locals=2, args_size=1
         0: aload_0
    *1   1: invokeinterface #1,  1            // InterfaceMethod log:()Ljava/lang/String;
         6: astore_1
         7: getstatic     #7                  // Field java/lang/System.out:Ljava/io/PrintStream;
        10: aload_1
        11: invokedynamic #13,  0             // InvokeDynamic #0:makeConcatWithConstants:(Ljava/lang/String;)Ljava/lang/String;
        16: invokevirtual #17                 // Method java/io/PrintStream.println:(Ljava/lang/String;)V
        19: return
      LineNumberTable:
        line 12: 0
        line 13: 7
        line 14: 19
}
SourceFile: "WorkFile.java"
BootstrapMethods:
  0: #47 REF_invokeStatic java/lang/invoke/StringConcatFactory.makeConcatWithConstants:(Ljava/lang/invoke/MethodHandles$Lookup;Ljava/lang/String;Ljava/lang/invoke/MethodType;Ljava/lang/String;[Ljava/lang/Object;)Ljava/lang/invoke/CallS
ite;
    Method arguments:
      #53 workingOn() with \u0001
InnerClasses:
  public static final #60= #56 of #58;    // Lookup=class java/lang/invoke/MethodHandles$Lookup of class java/lang/invoke/MethodHandles

------------------
*1 - interface 내의 구현된 method를 호출하는 instruction
    호출하는 method를 위한 정보를 otherbytes로 가짐 - ex) count(required stack size for passing nargs arguments)
    * 따라서 count, 즉 stack size는 항상 0보다 큼 (this를 넘기므로)
    https://stackoverflow.com/questions/56644884/invokeinterface-count-value

    *** 인터페이스 내에서 정의한 private 메서드는 ref 정보로써만 기록됨
    -> default 메서드는 인터페이스의 바이트 코드 내에서 바로 기록되지만, private 메서드는 외부로부터 호출하는 것 같음