Classfile /C:/Users/INSUNG/Documents/dev/JVM-Compiler-ByteCode/javap/src/main/sourcecode/innerAdvanced/OuterClass$InstanceClass.class
  Last modified 2023. 4. 22.; size 1450 bytes
  SHA-256 checksum df0f28f33751532cf8c0add4c8aa698935315f80a388075b091430f16182af5d
  Compiled from "OuterClass.java"
public class main.sourcecode.innerAdvanced.OuterClass$InstanceClass
  minor version: 0
  major version: 61
  flags: (0x0021) ACC_PUBLIC, ACC_SUPER
  this_class: #2                          // main/sourcecode/innerAdvanced/OuterClass$InstanceClass
  super_class: #8                         // java/lang/Object
  interfaces: 0, fields: 3, methods: 4, attributes: 4
Constant pool:
   #1 = Fieldref           #2.#3          // main/sourcecode/innerAdvanced/OuterClass$InstanceClass.this$0:Lmain/sourcecode/innerAdvanced/OuterClass;
   #2 = Class              #4             // main/sourcecode/innerAdvanced/OuterClass$InstanceClass
   #3 = NameAndType        #5:#6          // this$0:Lmain/sourcecode/innerAdvanced/OuterClass;
   #4 = Utf8               main/sourcecode/innerAdvanced/OuterClass$InstanceClass
   #5 = Utf8               this$0
   #6 = Utf8               Lmain/sourcecode/innerAdvanced/OuterClass;
   #7 = Methodref          #8.#9          // java/lang/Object."<init>":()V
   #8 = Class              #10            // java/lang/Object
   #9 = NameAndType        #11:#12        // "<init>":()V
  #10 = Utf8               java/lang/Object
  #11 = Utf8               <init>
  #12 = Utf8               ()V
  #13 = Fieldref           #14.#15        // java/lang/System.out:Ljava/io/PrintStream;
  #14 = Class              #16            // java/lang/System
  #15 = NameAndType        #17:#18        // out:Ljava/io/PrintStream;
  #16 = Utf8               java/lang/System
  #17 = Utf8               out
  #18 = Utf8               Ljava/io/PrintStream;
  #19 = Fieldref           #2.#20         // main/sourcecode/innerAdvanced/OuterClass$InstanceClass.a:I
  #20 = NameAndType        #21:#22        // a:I
  #21 = Utf8               a
  #22 = Utf8               I
  #23 = InvokeDynamic      #0:#24         // #0:makeConcatWithConstants:(I)Ljava/lang/String;
  #24 = NameAndType        #25:#26        // makeConcatWithConstants:(I)Ljava/lang/String;
  #25 = Utf8               makeConcatWithConstants
  #26 = Utf8               (I)Ljava/lang/String;
  #27 = Methodref          #28.#29        // java/io/PrintStream.println:(Ljava/lang/String;)V
  #28 = Class              #30            // java/io/PrintStream
  #29 = NameAndType        #31:#32        // println:(Ljava/lang/String;)V
  #30 = Utf8               java/io/PrintStream
  #31 = Utf8               println
  #32 = Utf8               (Ljava/lang/String;)V
  #33 = Fieldref           #2.#34         // main/sourcecode/innerAdvanced/OuterClass$InstanceClass.b:Ljava/lang/String;
  #34 = NameAndType        #35:#36        // b:Ljava/lang/String;
  #35 = Utf8               b
  #36 = Utf8               Ljava/lang/String;
  #37 = InvokeDynamic      #1:#38         // #1:makeConcatWithConstants:(Ljava/lang/String;)Ljava/lang/String;
  #38 = NameAndType        #25:#39        // makeConcatWithConstants:(Ljava/lang/String;)Ljava/lang/String;
  #39 = Utf8               (Ljava/lang/String;)Ljava/lang/String;
  #40 = String             #41            // InstaceClass 필드 b
  #41 = Utf8               InstaceClass 필드 b
  #42 = Utf8               (Lmain/sourcecode/innerAdvanced/OuterClass;)V
  #43 = Utf8               Code
  #44 = Utf8               LineNumberTable
  #45 = Utf8               method1
  #46 = Utf8               method2
  #47 = Utf8               <clinit>
  #48 = Utf8               SourceFile
  #49 = Utf8               OuterClass.java
  #50 = Utf8               NestHost
  #51 = Class              #52            // main/sourcecode/innerAdvanced/OuterClass
  #52 = Utf8               main/sourcecode/innerAdvanced/OuterClass
  #53 = Utf8               BootstrapMethods
  #54 = MethodHandle       6:#55          // REF_invokeStatic java/lang/invoke/StringConcatFactory.makeConcatWithConstants:(Ljava/lang/invoke/MethodHandles$Lookup;Ljava/lang/String;Ljava/lang/invoke/MethodType;Ljava/lang/String;[Ljava/
lang/Object;)Ljava/lang/invoke/CallSite;
  #55 = Methodref          #56.#57        // java/lang/invoke/StringConcatFactory.makeConcatWithConstants:(Ljava/lang/invoke/MethodHandles$Lookup;Ljava/lang/String;Ljava/lang/invoke/MethodType;Ljava/lang/String;[Ljava/lang/Object;)Ljav
a/lang/invoke/CallSite;
  #56 = Class              #58            // java/lang/invoke/StringConcatFactory
  #57 = NameAndType        #25:#59        // makeConcatWithConstants:(Ljava/lang/invoke/MethodHandles$Lookup;Ljava/lang/String;Ljava/lang/invoke/MethodType;Ljava/lang/String;[Ljava/lang/Object;)Ljava/lang/invoke/CallSite;
  #58 = Utf8               java/lang/invoke/StringConcatFactory
  #59 = Utf8               (Ljava/lang/invoke/MethodHandles$Lookup;Ljava/lang/String;Ljava/lang/invoke/MethodType;Ljava/lang/String;[Ljava/lang/Object;)Ljava/lang/invoke/CallSite;
  #60 = String             #61            // Instance Class Field variable : \u0001
  #61 = Utf8               Instance Class Field variable : \u0001
  #62 = String             #63            // static method 호출 : InstanceClass static 필드 b : \u0001
  #63 = Utf8               static method 호출 : InstanceClass static 필드 b : \u0001
  #64 = Utf8               InnerClasses
  #65 = Utf8               InstanceClass
  #66 = Class              #67            // java/lang/invoke/MethodHandles$Lookup
  #67 = Utf8               java/lang/invoke/MethodHandles$Lookup
  #68 = Class              #69            // java/lang/invoke/MethodHandles
  #69 = Utf8               java/lang/invoke/MethodHandles
  #70 = Utf8               Lookup
{
  public int a;
    descriptor: I
    flags: (0x0001) ACC_PUBLIC

  public static java.lang.String b;
    descriptor: Ljava/lang/String;
    flags: (0x0009) ACC_PUBLIC, ACC_STATIC

  final main.sourcecode.innerAdvanced.OuterClass this$0;
    descriptor: Lmain/sourcecode/innerAdvanced/OuterClass;
    flags: (0x1010) ACC_FINAL, ACC_SYNTHETIC

  public main.sourcecode.innerAdvanced.OuterClass$InstanceClass(main.sourcecode.innerAdvanced.OuterClass);
    descriptor: (Lmain/sourcecode/innerAdvanced/OuterClass;)V
    flags: (0x0001) ACC_PUBLIC
    Code:
      stack=2, locals=2, args_size=2
         0: aload_0
         1: aload_1
         2: putfield      #1                  // Field this$0:Lmain/sourcecode/innerAdvanced/OuterClass;
         5: aload_0
         6: invokespecial #7                  // Method java/lang/Object."<init>":()V
         9: return
      LineNumberTable:
        line 5: 0

  public void method1();
    descriptor: ()V
    flags: (0x0001) ACC_PUBLIC
    Code:
      stack=2, locals=1, args_size=1
         0: getstatic     #13                 // Field java/lang/System.out:Ljava/io/PrintStream;
         3: aload_0
         4: getfield      #19                 // Field a:I
         7: invokedynamic #23,  0             // InvokeDynamic #0:makeConcatWithConstants:(I)Ljava/lang/String;
        12: invokevirtual #27                 // Method java/io/PrintStream.println:(Ljava/lang/String;)V
        15: return
      LineNumberTable:
        line 11: 0
        line 12: 15

  public static void method2();
    descriptor: ()V
    flags: (0x0009) ACC_PUBLIC, ACC_STATIC
    Code:
      stack=2, locals=0, args_size=0
         0: getstatic     #13                 // Field java/lang/System.out:Ljava/io/PrintStream;
         3: getstatic     #33                 // Field b:Ljava/lang/String;
         6: invokedynamic #37,  0             // InvokeDynamic #1:makeConcatWithConstants:(Ljava/lang/String;)Ljava/lang/String;
        11: invokevirtual #27                 // Method java/io/PrintStream.println:(Ljava/lang/String;)V
        14: return
      LineNumberTable:
        line 15: 0
        line 16: 14

  static {};
    descriptor: ()V
    flags: (0x0008) ACC_STATIC
    Code:
      stack=1, locals=0, args_size=0
         0: ldc           #40                 // String InstaceClass 필드 b
         2: putstatic     #33                 // Field b:Ljava/lang/String;
         5: return
      LineNumberTable:
        line 8: 0
}
SourceFile: "OuterClass.java"
NestHost: class main/sourcecode/innerAdvanced/OuterClass
BootstrapMethods:
  0: #54 REF_invokeStatic java/lang/invoke/StringConcatFactory.makeConcatWithConstants:(Ljava/lang/invoke/MethodHandles$Lookup;Ljava/lang/String;Ljava/lang/invoke/MethodType;Ljava/lang/String;[Ljava/lang/Object;)Ljava/lang/invoke/CallS
ite;
    Method arguments:
      #60 Instance Class Field variable : \u0001
  1: #54 REF_invokeStatic java/lang/invoke/StringConcatFactory.makeConcatWithConstants:(Ljava/lang/invoke/MethodHandles$Lookup;Ljava/lang/String;Ljava/lang/invoke/MethodType;Ljava/lang/String;[Ljava/lang/Object;)Ljava/lang/invoke/CallS
ite;
    Method arguments:
      #62 static method 호출 : InstanceClass static 필드 b : \u0001
InnerClasses:
  public #65= #2 of #51;                  // InstanceClass=class main/sourcecode/innerAdvanced/OuterClass$InstanceClass of class main/sourcecode/innerAdvanced/OuterClass
  public static final #70= #66 of #68;    // Lookup=class java/lang/invoke/MethodHandles$Lookup of class java/lang/invoke/MethodHandles
